gistflow/__init__.py
gistflow/cli.py
gistflow/client.py
gistflow/errors.py
gistflow/types.py
gistflow-0.1.1.dist-info/licenses/LICENSE
gistflow-0.1.1.dist-info/METADATA
gistflow-0.1.1.dist-info/WHEEL
gistflow-0.1.1.dist-info/entry_points.txt
gistflow-0.1.1.dist-info/top_level.txt
gistflow-0.1.1.dist-info/RECORD
