Metadata-Version: 2.4
Name: gistflow
Version: 0.1.1
Summary: Tiny state sync over GitHub Gists (ETag-aware).
Author: Your Name
License: MIT
Requires-Python: >=3.9
License-File: LICENSE
Requires-Dist: requests>=2.31.0
Dynamic: license-file
